demucs_acapella/__init__.py
demucs_acapella/demucs_acapella.py
demucs_acapella-1.0.3.dist-info/LICENSE
demucs_acapella-1.0.3.dist-info/METADATA
demucs_acapella-1.0.3.dist-info/WHEEL
demucs_acapella-1.0.3.dist-info/entry_points.txt
demucs_acapella-1.0.3.dist-info/top_level.txt
demucs_acapella-1.0.3.dist-info/RECORD
